README.md
setup.py
simplekml/__init__.py
simplekml/abstractview.py
simplekml/base.py
simplekml/constants.py
simplekml/coordinates.py
simplekml/featgeom.py
simplekml/icon.py
simplekml/kml.py
simplekml/makeunicode.py
simplekml/model.py
simplekml/networklinkcontrol.py
simplekml/overlay.py
simplekml/region.py
simplekml/schema.py
simplekml/styleselector.py
simplekml/substyle.py
simplekml/timeprimitive.py
simplekml/tour.py
simplekml2_for_python3.egg-info/PKG-INFO
simplekml2_for_python3.egg-info/SOURCES.txt
simplekml2_for_python3.egg-info/dependency_links.txt
simplekml2_for_python3.egg-info/top_level.txt